anaconda_auth/__init__.py
anaconda_auth/__main__.py
anaconda_auth/_version.py
anaconda_auth/actions.py
anaconda_auth/adapters.py
anaconda_auth/cli.py
anaconda_auth/client.py
anaconda_auth/config.py
anaconda_auth/device_flow.py
anaconda_auth/exceptions.py
anaconda_auth/handlers.py
anaconda_auth/panel.py
anaconda_auth/py.typed
anaconda_auth/repo.py
anaconda_auth/token.py
anaconda_auth/utils.py
anaconda_auth/_conda/__init__.py
anaconda_auth/_conda/auth_handler.py
anaconda_auth/_conda/conda_api.py
anaconda_auth/_conda/conda_token.py
anaconda_auth/_conda/condarc.py
anaconda_auth/_conda/config.py
anaconda_auth/_conda/entrypoint.py
anaconda_auth/_conda/plugins.py
anaconda_auth/_conda/repo_config.py
anaconda_cloud_auth/__init__.py
anaconda_cloud_auth/actions.py
anaconda_cloud_auth/cli.py
anaconda_cloud_auth/client.py
anaconda_cloud_auth/config.py
anaconda_cloud_auth/exceptions.py
anaconda_cloud_auth/handlers.py
anaconda_cloud_auth/py.typed
anaconda_cloud_auth/token.py
anaconda_auth-0.12.2.dist-info/METADATA
anaconda_auth-0.12.2.dist-info/WHEEL
anaconda_auth-0.12.2.dist-info/entry_points.txt
anaconda_auth-0.12.2.dist-info/licenses/LICENSE
anaconda_auth-0.12.2.dist-info/RECORD
