Metadata-Version: 2.4
Name: anaconda-auth
Version: 0.12.2
Summary: A client auth library for Anaconda APIs
Project-URL: documentation, https://anaconda.github.io/anaconda-auth
Project-URL: homepage, https://anaconda.com
Project-URL: issues, https://github.com/anaconda/anaconda-auth/issues
Project-URL: repository, https://github.com/anaconda/anaconda-auth
License: BSD-3-Clause
License-File: LICENSE
Requires-Python: >=3.9
Requires-Dist: anaconda-cli-base>=0.7.0
Requires-Dist: cryptography>=3.4.0
Requires-Dist: keyring
Requires-Dist: pkce
Requires-Dist: pydantic
Requires-Dist: pyjwt
Requires-Dist: python-dotenv
Requires-Dist: requests
Requires-Dist: semver<4
Provides-Extra: dev
Requires-Dist: mypy; extra == 'dev'
Requires-Dist: pytest; extra == 'dev'
Requires-Dist: pytest-cov; extra == 'dev'
Requires-Dist: pytest-mock; extra == 'dev'
Requires-Dist: requests-mock; extra == 'dev'
Requires-Dist: responses; extra == 'dev'
Requires-Dist: tox; extra == 'dev'
Requires-Dist: types-requests; extra == 'dev'
Provides-Extra: publish
Requires-Dist: build; extra == 'publish'
Requires-Dist: twine; extra == 'publish'
Requires-Dist: wheel; extra == 'publish'
